evtxtocsv/__init__.py
evtxtocsv/evtxtocsv.py
evtxtocsv-0.2.0.dist-info/licenses/LICENSE
evtxtocsv-0.2.0.dist-info/METADATA
evtxtocsv-0.2.0.dist-info/WHEEL
evtxtocsv-0.2.0.dist-info/top_level.txt
evtxtocsv-0.2.0.dist-info/RECORD
