Metadata-Version: 2.4
Name: evtxtocsv
Version: 0.2.0
Summary: A tool to convert EVTX event logs to CSV format.
Author: Mustafa Selçuk Akbaş
Author-email: Mustafa Selçuk Akbaş <akbasselcuk32@gmail.com>
License: MIT
Project-URL: Bug Tracker, https://github.com/MSelcukAkbas/EVTX2CSV/issues
Project-URL: Source, https://github.com/MSelcukAkbas/EVTX2CSV
Keywords: EVTX,CSV,converter
License-File: LICENSE
Dynamic: author
Dynamic: license-file
